<?xml version="1.0" encoding="utf-8"?>
<doctrine-mapping xmlns="http://doctrine-project.org/schemas/orm/doctrine-mapping" xmlns:xsi="http://www.w3.org/2001/XMLSchema-instance" xsi:schemaLocation="http://doctrine-project.org/schemas/orm/doctrine-mapping http://doctrine-project.org/schemas/orm/doctrine-mapping.xsd">
  <entity name="Geolocation\AdminBundle\Entity\Ressources" table="ressources">
    <indexes>
      <index name="IDX_6A2CD5C7A76ED395" columns="user_id"/>
      <index name="IDX_6A2CD5C7413D8865" columns="cpf_id"/>
    </indexes>
    <id name="id" type="integer" column="id">
      <generator strategy="IDENTITY"/>
    </id>
    <field name="besoin" type="boolean" column="besoin" nullable="false"/>
    <many-to-one field="user" target-entity="User" fetch="LAZY">
      <join-columns>
        <join-column name="user_id" referenced-column-name="id"/>
      </join-columns>
    </many-to-one>
    <many-to-one field="cpf" target-entity="Cpf" fetch="LAZY">
      <join-columns>
        <join-column name="cpf_id" referenced-column-name="id"/>
      </join-columns>
    </many-to-one>
  </entity>
</doctrine-mapping>
